catapult_api/__init__.py
catapult_api/catapultAPI.py
catapult_api/transformers.py
catapult_api-0.6.3.dist-info/LICENSE
catapult_api-0.6.3.dist-info/METADATA
catapult_api-0.6.3.dist-info/WHEEL
catapult_api-0.6.3.dist-info/top_level.txt
catapult_api-0.6.3.dist-info/RECORD
