Metadata-Version: 2.1
Name: catapult-api
Version: 0.6.3
Summary: Python API wrapper for Catapult GPS tracking system
Author: Christian Rønsholt
Author-email: chr@fcn.dk
License-File: LICENSE
Requires-Dist: setuptools ==58.0.3
Requires-Dist: requests <=2.26.0
Requires-Dist: numpy <=1.24.1
Requires-Dist: pandas <=1.5.2
Provides-Extra: test
Requires-Dist: pytest <7,>=6.2.5 ; extra == 'test'
Requires-Dist: black ==22.3.0 ; extra == 'test'
